com/google/common/annotations/Beta.py
com/google/common/annotations/GwtCompatible.py
com/google/common/annotations/GwtIncompatible.py
com/google/common/annotations/VisibleForTesting.py
com/google/common/annotations/__init__.py
com/google/common/base/Absent.py
com/google/common/base/AbstractIterator.py
com/google/common/base/Ascii.py
com/google/common/base/CaseFormat.py
com/google/common/base/CharMatcher.py
com/google/common/base/Charsets.py
com/google/common/base/CommonMatcher.py
com/google/common/base/CommonPattern.py
com/google/common/base/Converter.py
com/google/common/base/Defaults.py
com/google/common/base/Enums.py
com/google/common/base/Equivalence.py
com/google/common/base/ExtraObjectsMethodsForWeb.py
com/google/common/base/FinalizablePhantomReference.py
com/google/common/base/FinalizableReference.py
com/google/common/base/FinalizableReferenceQueue.py
com/google/common/base/FinalizableSoftReference.py
com/google/common/base/FinalizableWeakReference.py
com/google/common/base/Function.py
com/google/common/base/FunctionalEquivalence.py
com/google/common/base/Functions.py
com/google/common/base/JdkPattern.py
com/google/common/base/Joiner.py
com/google/common/base/MoreObjects.py
com/google/common/base/Objects.py
com/google/common/base/Optional.py
com/google/common/base/PairwiseEquivalence.py
com/google/common/base/PatternCompiler.py
com/google/common/base/Platform.py
com/google/common/base/Preconditions.py
com/google/common/base/Predicate.py
com/google/common/base/Predicates.py
com/google/common/base/Present.py
com/google/common/base/SmallCharMatcher.py
com/google/common/base/Splitter.py
com/google/common/base/StandardSystemProperty.py
com/google/common/base/Stopwatch.py
com/google/common/base/Strings.py
com/google/common/base/Supplier.py
com/google/common/base/Suppliers.py
com/google/common/base/Throwables.py
com/google/common/base/Ticker.py
com/google/common/base/Utf8.py
com/google/common/base/Verify.py
com/google/common/base/VerifyException.py
spigot_sources-1.17.1.dist-info/LICENSE
spigot_sources-1.17.1.dist-info/METADATA
spigot_sources-1.17.1.dist-info/WHEEL
spigot_sources-1.17.1.dist-info/top_level.txt
spigot_sources-1.17.1.dist-info/RECORD
